patchymcpatchface/__init__.py
patchymcpatchface/apply_patch.py
patchymcpatchface/hooks.py
patchymcpatchface/utils/__init__.py
patchymcpatchface/utils/as_module.py
patchymcpatchface/utils/increase_recursion_limit.py
patchymcpatchface/utils/inspect_object_type.py
patchymcpatchface-0.1.19.dist-info/LICENSE
patchymcpatchface-0.1.19.dist-info/METADATA
patchymcpatchface-0.1.19.dist-info/WHEEL
patchymcpatchface-0.1.19.dist-info/top_level.txt
patchymcpatchface-0.1.19.dist-info/RECORD
