Metadata-Version: 2.1
Name: patchymcpatchface
Version: 0.1.19
Summary: A monkey patching library that uses only Python standard library
Home-page: https://github.com/foorenxiang/patchymcpatchface
Author: Ren Xiang Foo
Author-email: foorenxiang@gmail.com
License: UNKNOWN
Project-URL: Bug Tracker, https://github.com/foorenxiang/patchymcpatchface/issues
Platform: UNKNOWN
Classifier: Programming Language :: Python :: 3
Classifier: License :: OSI Approved :: MIT License
Classifier: Operating System :: OS Independent
Requires-Python: >=3.6
License-File: LICENSE
